topican/__init__.py
topican/topican_by_nouns.py
topican/topican_by_nouns_on_csv.py
topican/tests/__init__.py
topican/tests/topican_test_usage.py
topican-0.0.24.data/data/images/readme_usage_output.png
topican-0.0.24.dist-info/DESCRIPTION.rst
topican-0.0.24.dist-info/METADATA
topican-0.0.24.dist-info/RECORD
topican-0.0.24.dist-info/WHEEL
topican-0.0.24.dist-info/entry_points.txt
topican-0.0.24.dist-info/metadata.json
topican-0.0.24.dist-info/top_level.txt
