Metadata-Version: 2.0
Name: topican
Version: 0.0.24
Summary: Topic analyser
Home-page: https://github.com/randkego/topican
Author: Richard Smith
Author-email: randkego@gmail.com
License: MIT
Platform: UNKNOWN
Classifier: Development Status :: 2 - Pre-Alpha
Classifier: Programming Language :: Python :: 3
Classifier: License :: OSI Approved :: MIT License
Classifier: Operating System :: OS Independent
Requires-Dist: pandas
Requires-Dist: nltk
Requires-Dist: spacy
